paybybot3/__init__.py
paybybot3/__main__.py
paybybot3/bot.py
paybybot3/config.py
paybybot3/notifs.py
paybybot3-0.1.5.dist-info/LICENSE
paybybot3-0.1.5.dist-info/METADATA
paybybot3-0.1.5.dist-info/WHEEL
paybybot3-0.1.5.dist-info/entry_points.txt
paybybot3-0.1.5.dist-info/top_level.txt
paybybot3-0.1.5.dist-info/RECORD
