Metadata-Version: 2.1
Name: paybybot3
Version: 0.1.5
Summary: CLI interface to https://www.paybyphone.fr/
Home-page: https://github.com/rklf/paybybot3
Author: rklf
Author-email: contact@rklf.fr
License: MIT
Classifier: Topic :: Utilities
Requires-Python: >=3.6
License-File: LICENSE
Requires-Dist: pyyaml
Requires-Dist: requests
Requires-Dist: click
Requires-Dist: apprise
